check_filter/__init__.py
check_filter/check.py
check_filter/cli.py
check_filter/py.typed
check_filter/utils.py
check_filter-2.5.2.dist-info/METADATA
check_filter-2.5.2.dist-info/WHEEL
check_filter-2.5.2.dist-info/entry_points.txt
check_filter-2.5.2.dist-info/licenses/LICENSE
check_filter-2.5.2.dist-info/RECORD
