Metadata-Version: 2.4
Name: check-filter
Version: 2.5.2
Summary: Check URLs that filtered (or not) in Iran.
License: MIT
License-File: LICENSE
Keywords: internet,censorship,filtering,dns,iran,blocked
Author: Arash Hatami
Author-email: hatamiarash7@gmail.com
Requires-Python: >=3.10,<4.0
Classifier: Development Status :: 5 - Production/Stable
Classifier: Environment :: Console
Classifier: Intended Audience :: Developers
Classifier: Intended Audience :: System Administrators
Classifier: License :: OSI Approved :: MIT License
Classifier: Operating System :: OS Independent
Classifier: Programming Language :: Python :: 3
Classifier: Programming Language :: Python :: 3.10
Classifier: Programming Language :: Python :: 3.11
Classifier: Programming Language :: Python :: 3.12
Classifier: Programming Language :: Python :: 3.13
Classifier: Programming Language :: Python :: 3.14
Classifier: Programming Language :: Python :: 3 :: Only
Classifier: Topic :: Internet :: Name Service (DNS)
Classifier: Topic :: Security
Classifier: Topic :: Software Development
Classifier: Topic :: Software Development :: Libraries
Classifier: Typing :: Typed
Requires-Dist: dnspython (>=2.4.0,<3.0.0)
Requires-Dist: typer[all] (>=0.20,<0.21)
Requires-Dist: validators (>=0.35,<0.36)
Project-URL: Bug Tracker, https://github.com/hatamiarash7/CheckFiltering/issues
Project-URL: Changelog, https://github.com/hatamiarash7/CheckFiltering/releases
Project-URL: Homepage, https://arash-hatami.ir
Project-URL: Repository, https://github.com/hatamiarash7/CheckFiltering
